[
    {
        "'id'":"1",
        "img":"../public/images/accounts 1.png",
        "title":"Account & Finance",
        "postNo":100
    },
    {
        "'id'":"2",
        "img":"../public/images/business 1.png",
        "title":"Creative Design",
        "postNo":150
    },
    {
        "'id'":"3",
        "img":"../public/images/social-media 1.png",
        "title":"Marketing & Sales",
        "postNo":200
    },
    {
        "'id'":"4",
        "img":"../public/images/chip 1.png",
        "title":"Engineering Job",
        "postNo":250
    }
]